MANIFEST.in
README.md
setup.py
jet_utilities.egg-info/PKG-INFO
jet_utilities.egg-info/SOURCES.txt
jet_utilities.egg-info/dependency_links.txt
jet_utilities.egg-info/requires.txt
jet_utilities.egg-info/top_level.txt
jutils/__init__.py
jutils/data_loading.py
jutils/data_loading_schema.yml
jutils/kinematic_functions.py
jutils/plotting.py
jutils/transformations.py